leochen_win_os_info_mcp/__init__.py
leochen_win_os_info_mcp/main.py
leochen_win_os_info_mcp-0.1.0.dist-info/METADATA
leochen_win_os_info_mcp-0.1.0.dist-info/WHEEL
leochen_win_os_info_mcp-0.1.0.dist-info/entry_points.txt
leochen_win_os_info_mcp-0.1.0.dist-info/top_level.txt
leochen_win_os_info_mcp-0.1.0.dist-info/RECORD
