Metadata-Version: 2.4
Name: leochen-win-os-info-mcp
Version: 0.1.0
Summary: A simple MCP server that provides host system information.
Author-email: LeoChen <315531813@qq.com>
Classifier: Programming Language :: Python :: 3
Classifier: License :: OSI Approved :: MIT License
Classifier: Operating System :: OS Independent
Requires-Python: >=3.8
Requires-Dist: fastmcp
